CHANGES.txt
MANIFEST.in
README.rst
setup.py
bamboo/__init__.py
bamboo/bambooapp.py
bamboo/config/__init__.py
bamboo/config/celeryconfig.py
bamboo/config/celeryconfig_test.py
bamboo/config/db.py
bamboo/config/routes.py
bamboo/config/settings.py
bamboo/controllers/__init__.py
bamboo/controllers/abstract_controller.py
bamboo/controllers/calculations.py
bamboo/controllers/datasets.py
bamboo/controllers/root.py
bamboo/controllers/version.py
bamboo/core/__init__.py
bamboo/core/aggregations.py
bamboo/core/aggregator.py
bamboo/core/calculator.py
bamboo/core/frame.py
bamboo/core/merge.py
bamboo/core/operations.py
bamboo/core/parser.py
bamboo/core/summary.py
bamboo/lib/__init__.py
bamboo/lib/async.py
bamboo/lib/datetools.py
bamboo/lib/decorators.py
bamboo/lib/exceptions.py
bamboo/lib/io.py
bamboo/lib/jsontools.py
bamboo/lib/mail.py
bamboo/lib/mongo.py
bamboo/lib/parsing.py
bamboo/lib/query_args.py
bamboo/lib/schema_builder.py
bamboo/lib/utils.py
bamboo/lib/version.py
bamboo/models/__init__.py
bamboo/models/abstract_model.py
bamboo/models/calculation.py
bamboo/models/dataset.py
bamboo/models/observation.py
bamboo/tests/controllers/__init__.py
bamboo/tests/controllers/test_abstract_controller.py
bamboo/tests/controllers/test_abstract_datasets.py
bamboo/tests/controllers/test_abstract_datasets_update.py
bamboo/tests/controllers/test_calculations.py
bamboo/tests/controllers/test_datasets.py
bamboo/tests/controllers/test_datasets_edit.py
bamboo/tests/controllers/test_datasets_from_schema.py
bamboo/tests/controllers/test_datasets_join.py
bamboo/tests/controllers/test_datasets_merge.py
bamboo/tests/controllers/test_datasets_plot.py
bamboo/tests/controllers/test_datasets_post_update.py
bamboo/tests/controllers/test_datasets_summary.py
bamboo/tests/controllers/test_datasets_ts_functions.py
bamboo/tests/controllers/test_datasets_update.py
bamboo/tests/controllers/test_datasets_update_with_aggs.py
bamboo/tests/controllers/test_datasets_update_with_calcs.py
bamboo_server.egg-info/PKG-INFO
bamboo_server.egg-info/SOURCES.txt
bamboo_server.egg-info/dependency_links.txt
bamboo_server.egg-info/requires.txt
bamboo_server.egg-info/top_level.txt
