Metadata-Version: 1.0
Name: bamboo-server
Version: 0.6.3
Summary: Dynamic data analysis over the web. The logic to your data dashboards.
Home-page: http://bamboo.io
Author: Modi Research Group
Author-email: info@modilabs.org
License: BSD 3-clause
Platform: UNKNOWN
